odoo/addons/l10n_es_aeat_mod182/README.rst
odoo/addons/l10n_es_aeat_mod182/__init__.py
odoo/addons/l10n_es_aeat_mod182/__manifest__.py
odoo/addons/l10n_es_aeat_mod182/controllers/__init__.py
odoo/addons/l10n_es_aeat_mod182/controllers/main.py
odoo/addons/l10n_es_aeat_mod182/data/aeat_export_mod182_data.xml
odoo/addons/l10n_es_aeat_mod182/data/aeat_export_mod182_partner_data.xml
odoo/addons/l10n_es_aeat_mod182/data/mail_template_data.xml
odoo/addons/l10n_es_aeat_mod182/data/regional_community_deduction_data.xml
odoo/addons/l10n_es_aeat_mod182/data/tax_code_map_mod182_data.xml
odoo/addons/l10n_es_aeat_mod182/docs/182_register_design.pdf
odoo/addons/l10n_es_aeat_mod182/i18n/ca.po
odoo/addons/l10n_es_aeat_mod182/i18n/es.po
odoo/addons/l10n_es_aeat_mod182/images/l10n_es_aeat_mod182.png
odoo/addons/l10n_es_aeat_mod182/models/__init__.py
odoo/addons/l10n_es_aeat_mod182/models/account_move.py
odoo/addons/l10n_es_aeat_mod182/models/mod182.py
odoo/addons/l10n_es_aeat_mod182/models/mod182_import_lines.py
odoo/addons/l10n_es_aeat_mod182/models/mod182_move.py
odoo/addons/l10n_es_aeat_mod182/models/mod182_partner.py
odoo/addons/l10n_es_aeat_mod182/models/regional_community_deduction.py
odoo/addons/l10n_es_aeat_mod182/models/res_partner.py
odoo/addons/l10n_es_aeat_mod182/readme/CONFIG.rst
odoo/addons/l10n_es_aeat_mod182/readme/CONTRIBUTORS.rst
odoo/addons/l10n_es_aeat_mod182/readme/DESCRIPTION.rst
odoo/addons/l10n_es_aeat_mod182/readme/INSTALL.rst
odoo/addons/l10n_es_aeat_mod182/readme/ROADMAP.rst
odoo/addons/l10n_es_aeat_mod182/readme/USAGE.rst
odoo/addons/l10n_es_aeat_mod182/security/ir.model.access.csv
odoo/addons/l10n_es_aeat_mod182/security/mod_182_security.xml
odoo/addons/l10n_es_aeat_mod182/static/description/icon.png
odoo/addons/l10n_es_aeat_mod182/static/description/icon_source.svg
odoo/addons/l10n_es_aeat_mod182/static/description/index.html
odoo/addons/l10n_es_aeat_mod182/static/src/img/182_bad.svg
odoo/addons/l10n_es_aeat_mod182/static/src/img/182_ok.svg
odoo_addon_l10n_es_aeat_mod182-16.0.1.5.0.1.dist-info/METADATA
odoo_addon_l10n_es_aeat_mod182-16.0.1.5.0.1.dist-info/WHEEL
odoo_addon_l10n_es_aeat_mod182-16.0.1.5.0.1.dist-info/top_level.txt
odoo_addon_l10n_es_aeat_mod182-16.0.1.5.0.1.dist-info/RECORD
