Metadata-Version: 2.1
Name: odoo-addon-l10n_es_aeat_mod182
Version: 16.0.1.5.0.1
Requires-Python: >=3.10
Requires-Dist: odoo-addon-account_tax_balance>=16.0dev,<16.1dev
Requires-Dist: odoo-addon-l10n_es_aeat>=16.0dev,<16.1dev
Requires-Dist: odoo>=16.0a,<16.1dev
Summary: AEAT modelo 182
Home-page: https://github.com/OCA/l10n-spain
License: AGPL-3
Author: Tecnativa,PESOL,Odoo Community Association (OCA)
Author-email: support@odoo-community.org
Classifier: Programming Language :: Python
Classifier: Framework :: Odoo
Classifier: Framework :: Odoo :: 16.0
Classifier: License :: OSI Approved :: GNU Affero General Public License v3
